essmc2utils/__init__.py
essmc2utils/config.py
essmc2utils/logger.py
essmc2utils/registry.py
essmc2utils/version.py
essmc2utils/file_systems/__init__.py
essmc2utils/file_systems/aliyun_oss_fs.py
essmc2utils/file_systems/base_fs.py
essmc2utils/file_systems/file_system.py
essmc2utils/file_systems/http_fs.py
essmc2utils/file_systems/local_fs.py
essmc2utils/file_systems/registry.py
essmc2utils/file_systems/utils.py
essmc2utils-0.0.2.dist-info/LICENSE
essmc2utils-0.0.2.dist-info/METADATA
essmc2utils-0.0.2.dist-info/WHEEL
essmc2utils-0.0.2.dist-info/top_level.txt
essmc2utils-0.0.2.dist-info/RECORD
